Metadata-Version: 2.1
Name: jk-typo3
Version: 0.2020.3.9
Summary: This module provides functions and classes to assist in working with Typo3 installations.
Home-page: https://github.com/jkpubsrc/python-module-jk-typo3
Author: Jürgen Knauth
Author-email: pubsrc@binary-overflow.de
License: Apache 2.0
Download-URL: https://github.com/jkpubsrc/python-module-jk-typo3/tarball/0.2020.3.9
Keywords: typo3,php
Platform: UNKNOWN
Classifier: Development Status :: 3 - Alpha
Classifier: License :: OSI Approved :: Apache Software License
